havij/__init__.py
havij/application/__init__.py
havij/application/ports.py
havij/application/services/__init__.py
havij/application/services/meal_service.py
havij/application/services/product_service.py
havij/application/services/user_service.py
havij/domain/__init__.py
havij/domain/model/__init__.py
havij/domain/model/meal.py
havij/domain/model/nutrients.py
havij/domain/model/product.py
havij/domain/model/user.py
havij/domain/rules.py
havij/infrastructure/__init__.py
havij/infrastructure/api/__init__.py
havij/infrastructure/api/catalog_adapter.py
havij/infrastructure/api/openfoodfacts_client.py
havij/infrastructure/config.py
havij/infrastructure/persistence/__init__.py
havij/infrastructure/persistence/meal_repository.py
havij/infrastructure/persistence/sqlite_db.py
havij/infrastructure/persistence/user_repository.py
havij/presentation/__init__.py
havij/presentation/pages/__init__.py
havij/presentation/streamlit_app.py
havij_nutrition-1.1.0.dist-info/METADATA
havij_nutrition-1.1.0.dist-info/WHEEL
havij_nutrition-1.1.0.dist-info/entry_points.txt
havij_nutrition-1.1.0.dist-info/licenses/LICENSE
havij_nutrition-1.1.0.dist-info/RECORD
