Metadata-Version: 2.4
Name: havij_nutrition
Version: 1.1.0
Summary: Hit your daily nutrition goals with Havij!
License: Apache 2.0
License-File: LICENSE
Author: Farideh Tavakoli
Author-email: farideh.tavakoli@studio.unibo.it
Requires-Python: >=3.10.0,<4.0.0
Classifier: License :: Other/Proprietary License
Classifier: Programming Language :: Python :: 3
Classifier: Programming Language :: Python :: 3.10
Classifier: Programming Language :: Python :: 3.11
Classifier: Programming Language :: Python :: 3.12
Classifier: Programming Language :: Python :: 3.13
Classifier: Programming Language :: Python :: 3.14
Requires-Dist: pandas (>=2.2.3,<3.0.0)
Requires-Dist: requests (>=2.32.5,<3.0.0)
Requires-Dist: streamlit (>=1.39.0,<2.0.0)
